dronesearch/__init__.py
dronesearch/dronefilter.py
dronesearch/inputsource.py
dronesearch/networkservice.py
dronesearch/onboard.py
dronesearch/onserver.py
dronesearch/utils.py
dronesearch-1.0.0.1.dist-info/LICENSE
dronesearch-1.0.0.1.dist-info/METADATA
dronesearch-1.0.0.1.dist-info/WHEEL
dronesearch-1.0.0.1.dist-info/top_level.txt
dronesearch-1.0.0.1.dist-info/RECORD
